pyvirtualname/__init__.py
pyvirtualname/client.py
pyvirtualname/config.py
pyvirtualname/exceptions.py
pyvirtualname-0.1.1.dist-info/METADATA
pyvirtualname-0.1.1.dist-info/RECORD
pyvirtualname-0.1.1.dist-info/WHEEL
pyvirtualname-0.1.1.dist-info/top_level.txt
