Metadata-Version: 2.1
Name: pyvirtualname
Version: 0.1.1
Summary: Wrapper for Virtualname API
Home-page: https://gitlab.com/carbans/pyvirtualname
Author: Carlos Latorre
Author-email: me@carloslatorre.net
License: GPL3
Platform: UNKNOWN
Classifier: Development Status :: 4 - Beta
Classifier: Programming Language :: Python :: 3
Requires-Dist: requests
